neirost4r/__init__.py
neirost4r/client.py
neirost4r-1.0.dist-info/METADATA
neirost4r-1.0.dist-info/WHEEL
neirost4r-1.0.dist-info/top_level.txt
neirost4r-1.0.dist-info/RECORD
