Metadata-Version: 2.4
Name: neirost4r
Version: 1.0
Summary: Python client for fenst4r.life API
Home-page: https://fenst4r.life
Author: FENST4R
Author-email: ddejjcat@internet.ru
Classifier: Programming Language :: Python :: 3
Classifier: License :: OSI Approved :: MIT License
Classifier: Operating System :: OS Independent
Requires-Python: >=3.8
Requires-Dist: requests>=2.28.0
Dynamic: author
Dynamic: author-email
Dynamic: classifier
Dynamic: description
Dynamic: description-content-type
Dynamic: home-page
Dynamic: requires-dist
Dynamic: requires-python
Dynamic: summary
